[
  {
    "name": "Monster Bone",
    "description": "A bone suitable for crafting.",
    "amount": 0,
    "type": "Basic",
    "existingCards": 4,
    "tags": [
      "bone"
    ]
  },
  {
    "name": "Monster Hide",
    "description": "The skin of a beast.",
    "amount": 0,
    "type": "Basic",
    "existingCards": 6,
    "tags": [
      "hide"
    ]
  },
  {
    "name": "Broken Lantern",
    "description": "Remains of an extinguished lantern.",
    "amount": 0,
    "type": "Basic",
    "existingCards": 1,
    "tags": [
      "scrap"
    ]
  },
  {
    "name": "???",
    "description": "You have no idea what monster bit this is. Can be used as bone, organ or hide",
    "amount": 0,
    "type": "Basic",
    "existingCards": 2,
    "tags": [
      "hide",
      "bone",
      "consumable",
      "organ"
    ]
  },
  {
    "name": "Skull",
    "description": "When you gain this, a survivors of your choice gains +1 insanity.",
    "amount": 0,
    "type": "Basic",
    "existingCards": 1,
    "tags": [
      "bone"
    ]
  },
  {
    "name": "Monster Organ",
    "description": "If you consume this, archive this card. Roll 1d10. On a result of 6+, you contract a parasite. Archive all consumable gear in your gear grid now.",
    "amount": 0,
    "type": "Basic",
    "existingCards": 3,
    "tags": [
      "organ",
      "consumable"
    ]
  },
  {
    "name": "Love Juice",
    "description": "During the settlement phase, you may archive this to Intimacy. Nominated survivors must be able to consume.",
    "amount": 0,
    "type": "Basic",
    "existingCards": 2,
    "tags": [
      "organ",
      "consumable"
    ]
  },
  {
    "name": "Elder Cat Teeth",
    "description": "As sharp as they are strange.",
    "amount": 0,
    "type": "Strange",
    "existingCards": 1,
    "tags": [
      "bone"
    ]
  },
  {
    "name": "Lion Tail",
    "description": "It's surprisingly heavy.",
    "amount": 0,
    "type": "WhiteLion",
    "existingCards": 1,
    "tags": [
      "hide"
    ]
  },
  {
    "name": "White Fur",
    "description": "Luxurious and soft to the touch.",
    "amount": 0,
    "type": "WhiteLion",
    "existingCards": 4,
    "tags": [
      "hide"
    ]
  },
  {
    "name": "Curious Hand",
    "description": "When you gain this a random survivor gains +1 insanity. Holding this fills you with sadness.",
    "amount": 0,
    "type": "WhiteLion",
    "existingCards": 1,
    "tags": [
      "hide"
    ]
  },
  {
    "name": "Great Cat Bones",
    "description": "Strong and surprisingly light.",
    "amount": 0,
    "type": "WhiteLion",
    "existingCards": 4,
    "tags": [
      "bone"
    ]
  },
  {
    "name": "Eye of Cat",
    "description": "A perfectly preserved eye.",
    "amount": 0,
    "type": "WhiteLion",
    "existingCards": 1,
    "tags": [
      "organ",
      "consumable"
    ]
  },
  {
    "name": "Sinew",
    "description": "These stringy guts are quite useful.",
    "amount": 0,
    "type": "WhiteLion",
    "existingCards": 2,
    "tags": [
      "organ"
    ]
  },
  {
    "name": "Lion Claw",
    "description": "A razor-sharp, retractable claw.",
    "amount": 0,
    "type": "WhiteLion",
    "existingCards": 3,
    "tags": [
      "bone"
    ]
  },
  {
    "name": "Lion Testes",
    "description": "A hefty pair of nuts.",
    "amount": 0,
    "type": "WhiteLion",
    "existingCards": 1,
    "tags": [
      "organ",
      "consumable"
    ]
  },
  {
    "name": "Shimmering Mane",
    "description": "Archive this to gain 2 basic hide resources. It shimmers in the lantern light.",
    "amount": 0,
    "type": "WhiteLion",
    "existingCards": 1,
    "tags": [
      "hide"
    ]
  },
  {
    "name": "Golden Whiskers",
    "description": "These whiskers are tough!",
    "amount": 0,
    "type": "WhiteLion",
    "existingCards": 1,
    "tags": [
      "organ"
    ]
  },
  {
    "name": "Pelt",
    "description": "Coarse and warm.",
    "amount": 0,
    "type": "ScreamingAntelope",
    "existingCards": 4,
    "tags": [
      "hide"
    ]
  },
  {
    "name": "Shank Bone",
    "description": "Strangely jointed.",
    "amount": 0,
    "type": "ScreamingAntelope",
    "existingCards": 4,
    "tags": [
      "bone"
    ]
  },
  {
    "name": "Beast Steak",
    "description": "Shockingly appetizing.",
    "amount": 0,
    "type": "ScreamingAntelope",
    "existingCards": 2,
    "tags": [
      "organ",
      "consumable"
    ]
  },
  {
    "name": "Large Flat Tooth",
    "description": "When you gain this, a survivor of your choice gains +1 insanity. Its surface is rough and bumpy.",
    "amount": 0,
    "type": "ScreamingAntelope",
    "existingCards": 2,
    "tags": [
      "bone"
    ]
  },
  {
    "name": "Spiral Horn",
    "description": "Moans balefully when blown.",
    "amount": 0,
    "type": "ScreamingAntelope",
    "existingCards": 1,
    "tags": [
      "bone"
    ]
  },
  {
    "name": "Screaming Brain",
    "description": "Consume: Archive this and gain survival up to the current limit",
    "amount": 0,
    "type": "ScreamingAntelope",
    "existingCards": 1,
    "tags": [
      "organ",
      "consumable"
    ]
  },
  {
    "name": "Muscly Gums",
    "description": "Difficult to pry apart",
    "amount": 0,
    "type": "ScreamingAntelope",
    "existingCards": 1,
    "tags": [
      "organ",
      "consumable"
    ]
  },
  {
    "name": "Bladder",
    "description": "Smells like urine",
    "amount": 0,
    "type": "ScreamingAntelope",
    "existingCards": 1,
    "tags": [
      "organ",
      "consumable"
    ]
  },
  {
    "name": "Pustules",
    "description": "The aroma is tempting.",
    "amount": 0,
    "type": "Phoenix",
    "existingCards": 2,
    "tags": [
      "organ",
      "consumable"
    ]
  },
  {
    "name": "Muculent Droppings",
    "description": "Delicately scented, papery husk.",
    "amount": 0,
    "type": "Phoenix",
    "existingCards": 3,
    "tags": [
      "organ"
    ]
  },
  {
    "name": "Hollow Wing Bones",
    "description": "Delicate and finely balanced.",
    "amount": 0,
    "type": "Phoenix",
    "existingCards": 3,
    "tags": [
      "bone"
    ]
  },
  {
    "name": "Tail Feathers",
    "description": "Lighter than air.",
    "amount": 0,
    "type": "Phoenix",
    "existingCards": 3,
    "tags": [
      "hide"
    ]
  },
  {
    "name": "Phoenix Finger",
    "description": "When you gain this, a survivor of your choice gains +3 insanity.",
    "amount": 0,
    "type": "Phoenix",
    "existingCards": 2,
    "tags": [
      "bone"
    ]
  },
  {
    "name": "Small Feathers",
    "description": "Soft interior with razor sharp edges.",
    "amount": 0,
    "type": "Phoenix",
    "existingCards": 3,
    "tags": [
      "hide"
    ]
  },
  {
    "name": "Phoenix Whisker",
    "description": "Silky, yet robust.",
    "amount": 0,
    "type": "Phoenix",
    "existingCards": 1,
    "tags": [
      "hide"
    ]
  },
  {
    "name": "Rainbow Droppings",
    "description": "Consume: Archive this and roll 1d10. On 7+, gain +1 permanent speed. Otherwise, your heart explodes, killing you instantly.",
    "amount": 0,
    "type": "Phoenix",
    "existingCards": 1,
    "tags": [
      "organ",
      "consumable"
    ]
  },
  {
    "name": "Phoenix Eye",
    "description": "Filled with a thick, metallic liquid.",
    "amount": 0,
    "type": "Phoenix",
    "existingCards": 1,
    "tags": [
      "organ",
      "scrap"
    ]
  },
  {
    "name": "Bird Beak",
    "description": "Surprisingly toothy.",
    "amount": 0,
    "type": "Phoenix",
    "existingCards": 1,
    "tags": [
      "bone"
    ]
  },
  {
    "name": "Wishbone",
    "description": "A delicate bone with a strange aura.",
    "amount": 0,
    "type": "Phoenix",
    "existingCards": 1,
    "tags": [
      "bone"
    ]
  },
  {
    "name": "Small Hand Parasites",
    "description": "Still wriggling.",
    "amount": 0,
    "type": "Phoenix",
    "existingCards": 1,
    "tags": [
      "organ"
    ]
  },
  {
    "name": "Black Skull",
    "description": "Aged to perfection.",
    "amount": 0,
    "type": "Phoenix",
    "existingCards": 1,
    "tags": [
      "iron",
      "skull",
      "bone"
    ]
  },
  {
    "name": "Shimmering Halo",
    "description": "Curiously heavy.",
    "amount": 0,
    "type": "Phoenix",
    "existingCards": 1,
    "tags": [
      "organ"
    ]
  },
  {
    "name": "Fresh Acanthus",
    "description": "Archive this to fully heal 1 hit location, including injury level and armor points.",
    "amount": 4,
    "type": "Strange",
    "existingCards": 1,
    "tags": [
      "herb"
    ]
  },
  {
    "name": "Legendary Horns",
    "description": "Holding them fills you with power.",
    "amount": 0,
    "type": "Strange",
    "existingCards": 1,
    "tags": [
      "bone",
      "scrap"
    ]
  },
  {
    "name": "Perfect Crucible",
    "description": "When you craft with Perfect Crucible, an ancient bacteria is released into the air. Suffer -1d10 population and archive this card.",
    "amount": 0,
    "type": "Strange",
    "existingCards": 1,
    "tags": [
      "iron"
    ]
  },
  {
    "name": "Phoenix Crest",
    "description": "Firm and supple.",
    "amount": 0,
    "type": "Strange",
    "existingCards": 1,
    "tags": [
      "organ"
    ]
  },
  {
    "name": "Second Heart",
    "description": "It still tries to bite you.",
    "amount": 0,
    "type": "Strange",
    "existingCards": 1,
    "tags": [
      "organ",
      "bone"
    ]
  },
  {
    "name": "Leather",
    "description": "Never goes out of style.",
    "amount": 0,
    "type": "Strange",
    "existingCards": 4,
    "tags": [
      "hide"
    ]
  },
  {
    "name": "Iron",
    "description": "Harder than bone.",
    "amount": 0,
    "type": "Strange",
    "existingCards": 8,
    "tags": [
      "scrap"
    ]
  }
]
